LICENSE.txt
MANIFEST.in
README.md
setup.py
python/jittor/__init__.py
python/jittor/__init__.pyi
python/jittor/attention.py
python/jittor/compile_extern.py
python/jittor/compiler.py
python/jittor/contrib.py
python/jittor/depthwise_conv.py
python/jittor/distributions.py
python/jittor/init.py
python/jittor/init_cupy.py
python/jittor/linalg.py
python/jittor/lr_scheduler.py
python/jittor/misc.py
python/jittor/nn.py
python/jittor/optim.py
python/jittor/pool.py
python/jittor/pyjt_compiler.py
python/jittor/sparse.py
python/jittor/version
python/jittor/dataset/__init__.py
python/jittor/dataset/cifar.py
python/jittor/dataset/dataset.py
python/jittor/dataset/mnist.py
python/jittor/dataset/sampler.py
python/jittor/dataset/utils.py
python/jittor/dataset/voc.py
python/jittor/demo/simple_cgan.py
python/jittor/extern/acl/acl_compiler.py
python/jittor/extern/acl/acl_error_code.cc
python/jittor/extern/acl/acl_jittor.cc
python/jittor/extern/acl/acl_jittor.h
python/jittor/extern/cuda/cub/inc/cub_test.h
python/jittor/extern/cuda/cub/ops/cub_arg_reduce_op.cc
python/jittor/extern/cuda/cub/ops/cub_arg_reduce_op.h
python/jittor/extern/cuda/cub/ops/cub_argsort_op.cc
python/jittor/extern/cuda/cub/ops/cub_argsort_op.h
python/jittor/extern/cuda/cub/ops/cub_cumsum_op.cc
python/jittor/extern/cuda/cub/ops/cub_cumsum_op.h
python/jittor/extern/cuda/cub/ops/cub_test_op.cc
python/jittor/extern/cuda/cub/ops/cub_test_op.h
python/jittor/extern/cuda/cub/ops/cub_where_op.cc
python/jittor/extern/cuda/cub/ops/cub_where_op.h
python/jittor/extern/cuda/cublas/inc/cublas_wrapper.h
python/jittor/extern/cuda/cublas/ops/cublas_acc_matmul_op.cc
python/jittor/extern/cuda/cublas/ops/cublas_acc_matmul_op.h
python/jittor/extern/cuda/cublas/ops/cublas_batched_matmul_op.cc
python/jittor/extern/cuda/cublas/ops/cublas_batched_matmul_op.h
python/jittor/extern/cuda/cublas/ops/cublas_matmul_op.cc
python/jittor/extern/cuda/cublas/ops/cublas_matmul_op.h
python/jittor/extern/cuda/cublas/ops/cublas_test_op.cc
python/jittor_rocm.egg-info/PKG-INFO
python/jittor_rocm.egg-info/SOURCES.txt
python/jittor_rocm.egg-info/dependency_links.txt
python/jittor_rocm.egg-info/requires.txt
python/jittor_rocm.egg-info/top_level.txt
