Metadata-Version: 2.1
Name: jittor-rocm
Version: 1.3.4.15
Summary: a Just-in-time(JIT) deep learning framework
Home-page: http://jittor.org
Author: Jittor Group
Author-email: ran.donglang@gmail.com
License: UNKNOWN
Platform: UNKNOWN
Requires-Python: >=3.7
License-File: LICENSE.txt
